{"commitInfo":{"timestamp":1670962873934,"userId":"4980270442223414","userName":"kevinbarvaliya@gmail.com","operation":"MERGE","operationParameters":{"predicate":"(((trg.race_id = src.race_id) AND (trg.driver_id = src.driver_id)) AND (trg.stop = src.stop))","matchedPredicates":"[{\"actionType\":\"update\"}]","notMatchedPredicates":"[{\"actionType\":\"insert\"}]"},"notebook":{"notebookId":"3991344529456479"},"clusterId":"1125-023945-d48qvzoh","readVersion":0,"isolationLevel":"WriteSerializable","isBlindAppend":false,"operationMetrics":{"numTargetRowsCopied":"0","numTargetRowsDeleted":"0","numTargetFilesAdded":"1","executionTimeMs":"29106","numTargetRowsInserted":"40","scanTimeMs":"27281","numTargetRowsUpdated":"0","numOutputRows":"40","numTargetChangeFilesAdded":"0","numSourceRows":"40","numTargetFilesRemoved":"0","rewriteTimeMs":"1671"},"engineInfo":"Databricks-Runtime/11.3.x-scala2.12","txnId":"f31288e7-f6c7-4b8b-88e5-dade0711e7b0"}}
{"add":{"path":"race_id=1052/part-00000-74608077-c89b-4084-bcf3-cd1008a6384b.c000.snappy.parquet","partitionValues":{"race_id":"1052"},"size":3732,"modificationTime":1670962873000,"dataChange":true,"stats":"{\"numRecords\":40,\"minValues\":{\"driver_id\":1,\"stop\":\"1\",\"lap\":2,\"time\":\"18:11:56\",\"duration\":\"23.848\",\"milliseconds\":23848,\"ingestion_date\":\"2022-12-13T20:20:44.821Z\",\"data_source\":\"test data\",\"file_date\":\"2021-03-28\"},\"maxValues\":{\"driver_id\":854,\"stop\":\"3\",\"lap\":54,\"time\":\"19:36:21\",\"duration\":\"38.338\",\"milliseconds\":38338,\"ingestion_date\":\"2022-12-13T20:20:44.821Z\",\"data_source\":\"test data\",\"file_date\":\"2021-03-28\"},\"nullCount\":{\"driver_id\":0,\"stop\":0,\"lap\":0,\"time\":0,\"duration\":0,\"milliseconds\":0,\"ingestion_date\":0,\"data_source\":0,\"file_date\":0}}","tags":{"INSERTION_TIME":"1670962873000000","MIN_INSERTION_TIME":"1670962873000000","MAX_INSERTION_TIME":"1670962873000000","OPTIMIZE_TARGET_SIZE":"268435456"}}}
